liblaf/mkdocs_preset/__init__.py
liblaf/mkdocs_preset/__init__.pyi
liblaf/mkdocs_preset/_version.py
liblaf/mkdocs_preset/_version.pyi
liblaf/mkdocs_preset/py.typed
liblaf_mkdocs_preset-0.3.1.dist-info/METADATA
liblaf_mkdocs_preset-0.3.1.dist-info/WHEEL
liblaf_mkdocs_preset-0.3.1.dist-info/licenses/LICENSE
liblaf_mkdocs_preset-0.3.1.dist-info/RECORD
