Metadata-Version: 2.4
Name: liblaf-mkdocs-preset
Version: 0.3.1
Project-URL: Changelog, https://github.com/liblaf/mkdocs-preset/blob/main/CHANGELOG.md
Project-URL: Documentation, https://liblaf.github.io/mkdocs-preset/
Project-URL: Funding, https://github.com/liblaf/mkdocs-preset?sponsor=1
Project-URL: Homepage, https://github.com/liblaf/mkdocs-preset
Project-URL: Issue Tracker, https://github.com/liblaf/mkdocs-preset/issues
Project-URL: Release Notes, https://github.com/liblaf/mkdocs-preset/releases
Project-URL: Source Code, https://github.com/liblaf/mkdocs-preset
Author-email: liblaf <30631553+liblaf@users.noreply.github.com>
License-Expression: MIT
License-File: LICENSE
Classifier: Development Status :: 4 - Beta
Classifier: Intended Audience :: Developers
Classifier: License :: OSI Approved
Classifier: License :: OSI Approved :: MIT License
Classifier: Operating System :: OS Independent
Classifier: Programming Language :: Python
Classifier: Programming Language :: Python :: 3
Classifier: Programming Language :: Python :: 3.12
Classifier: Programming Language :: Python :: 3.13
Classifier: Programming Language :: Python :: 3.14
Classifier: Typing :: Typed
Requires-Python: >=3.12
Requires-Dist: griffe-fieldz<0.5,>=0.4
Requires-Dist: griffe-inherited-docstrings<2,>=1
Requires-Dist: griffe-pydantic<2,>=1
Requires-Dist: griffe-warnings-deprecated<2,>=1
Requires-Dist: mdx-truly-sane-lists<2,>=1
Requires-Dist: mkdocs-api-autonav<0.5,>=0.4
Requires-Dist: mkdocs-autorefs<2,>=1
Requires-Dist: mkdocs-awesome-nav<4,>=3
Requires-Dist: mkdocs-git-committers-plugin-2<3,>=2
Requires-Dist: mkdocs-git-revision-date-localized-plugin<2,>=1
Requires-Dist: mkdocs-include-markdown-plugin[cache]<8,>=7
Requires-Dist: mkdocs-material[imaging]<10,>=9
Requires-Dist: mkdocs<2,>=1
Requires-Dist: mkdocstrings[python]<2,>=1
Requires-Dist: pymdown-extensions<11,>=10
Requires-Dist: ruff<0.15,>=0.14
